cmo_nnect/__init__.py
cmo_nnect/afasprofit.py
cmo_nnect/nmbrs.py
cmo_nnect-0.0.1.dist-info/LICENSE
cmo_nnect-0.0.1.dist-info/METADATA
cmo_nnect-0.0.1.dist-info/WHEEL
cmo_nnect-0.0.1.dist-info/top_level.txt
cmo_nnect-0.0.1.dist-info/RECORD
