Metadata-Version: 2.1
Name: cmo-nnect
Version: 0.0.1
Summary: Connector with a variety of API's with ease.
Home-page: https://dev.azure.com/Cmotions/Packages/_git/DriveScanner
Author: Thijs van der Velden, Koen Leijsten
Author-email: service@cmotions.nl
License: UNKNOWN
Platform: UNKNOWN
Requires-Python: >=3.9
Requires-Dist: pandas
Requires-Dist: requests
Requires-Dist: base64
Requires-Dist: zeep
Provides-Extra: dev
Requires-Dist: black ; extra == 'dev'
Requires-Dist: jupyterlab ; extra == 'dev'
Requires-Dist: pytest (>=6.2.4) ; extra == 'dev'
Requires-Dist: python-dotenv ; extra == 'dev'
Requires-Dist: ipykernel ; extra == 'dev'
Requires-Dist: twine ; extra == 'dev'
